supirfactor_dynamical/__init__.py
supirfactor_dynamical/_io/__init__.py
supirfactor_dynamical/_io/_args.py
supirfactor_dynamical/_io/_loader.py
supirfactor_dynamical/_io/_network.py
supirfactor_dynamical/_io/_torch_state.py
supirfactor_dynamical/_io/_writer.py
supirfactor_dynamical/_io/load_data.py
supirfactor_dynamical/_utils/__init__.py
supirfactor_dynamical/_utils/_adata_load.py
supirfactor_dynamical/_utils/_loader.py
supirfactor_dynamical/_utils/_math.py
supirfactor_dynamical/_utils/_trunc_robust_scaler.py
supirfactor_dynamical/_utils/_utils.py
supirfactor_dynamical/_utils/activation.py
supirfactor_dynamical/_utils/early_stopping.py
supirfactor_dynamical/_utils/misc.py
supirfactor_dynamical/_utils/time_offsets.py
supirfactor_dynamical/datasets/__init__.py
supirfactor_dynamical/datasets/anndata_backed_dataset.py
supirfactor_dynamical/datasets/stratified_file_dataset.py
supirfactor_dynamical/datasets/time_dataset.py
supirfactor_dynamical/models/__init__.py
supirfactor_dynamical/models/_base_model.py
supirfactor_dynamical/models/_base_recurrent_model.py
supirfactor_dynamical/models/ae_model.py
supirfactor_dynamical/models/biophysical_model.py
supirfactor_dynamical/models/chromatin_model.py
supirfactor_dynamical/models/decay_model.py
supirfactor_dynamical/models/modules.py
supirfactor_dynamical/models/recurrent_models.py
supirfactor_dynamical/models/simple_models.py
supirfactor_dynamical/models/_model_mixins/__init__.py
supirfactor_dynamical/models/_model_mixins/multiencoder_mixin.py
supirfactor_dynamical/models/_model_mixins/multimodal_data_mixin.py
supirfactor_dynamical/models/_model_mixins/prior_mixin.py
supirfactor_dynamical/models/_model_mixins/scaling_mixin.py
supirfactor_dynamical/models/_model_mixins/time_offset_mixins.py
supirfactor_dynamical/models/_model_mixins/training_mixin.py
supirfactor_dynamical/models/_model_mixins/velocity_mixin.py
supirfactor_dynamical/perturbation/__init__.py
supirfactor_dynamical/perturbation/backprop_error.py
supirfactor_dynamical-1.1.0.dist-info/LICENSE
supirfactor_dynamical-1.1.0.dist-info/METADATA
supirfactor_dynamical-1.1.0.dist-info/WHEEL
supirfactor_dynamical-1.1.0.dist-info/top_level.txt
supirfactor_dynamical-1.1.0.dist-info/RECORD
