Metadata-Version: 2.1
Name: supirfactor_dynamical
Version: 1.1.0
Summary: Dynamical Model Extension of the Supirfactor Model
Home-page: https://github.com/GreshamLab/supirfactor-dynamical
Author: Chris Jackson
Author-email: cj59@nyu.edu
Maintainer: Chris Jackson
Maintainer-email: cj59@nyu.edu
License-File: LICENSE
Requires-Dist: numpy
Requires-Dist: pandas>=1.0
Requires-Dist: anndata>=0.8
Requires-Dist: tqdm
Requires-Dist: torch
Requires-Dist: scipy
Requires-Dist: inferelator
